SpiffWorkflow/__init__.py
SpiffWorkflow/exceptions.py
SpiffWorkflow/operators.py
SpiffWorkflow/task.py
SpiffWorkflow/version.py
SpiffWorkflow/workflow.py
SpiffWorkflow/bpmn/__init__.py
SpiffWorkflow/bpmn/exceptions.py
SpiffWorkflow/bpmn/workflow.py
SpiffWorkflow/bpmn/parser/BpmnParser.py
SpiffWorkflow/bpmn/parser/ProcessParser.py
SpiffWorkflow/bpmn/parser/TaskParser.py
SpiffWorkflow/bpmn/parser/ValidationException.py
SpiffWorkflow/bpmn/parser/__init__.py
SpiffWorkflow/bpmn/parser/event_parsers.py
SpiffWorkflow/bpmn/parser/node_parser.py
SpiffWorkflow/bpmn/parser/spec_description.py
SpiffWorkflow/bpmn/parser/task_parsers.py
SpiffWorkflow/bpmn/parser/util.py
SpiffWorkflow/bpmn/parser/schema/BPMN20.xsd
SpiffWorkflow/bpmn/parser/schema/BPMNDI.xsd
SpiffWorkflow/bpmn/parser/schema/DC.xsd
SpiffWorkflow/bpmn/parser/schema/DI.xsd
SpiffWorkflow/bpmn/parser/schema/Semantic.xsd
SpiffWorkflow/bpmn/script_engine/__init__.py
SpiffWorkflow/bpmn/script_engine/python_engine.py
SpiffWorkflow/bpmn/script_engine/python_environment.py
SpiffWorkflow/bpmn/serializer/__init__.py
SpiffWorkflow/bpmn/serializer/config.py
SpiffWorkflow/bpmn/serializer/exceptions.py
SpiffWorkflow/bpmn/serializer/workflow.py
SpiffWorkflow/bpmn/serializer/default/__init__.py
SpiffWorkflow/bpmn/serializer/default/event_definition.py
SpiffWorkflow/bpmn/serializer/default/process_spec.py
SpiffWorkflow/bpmn/serializer/default/task_spec.py
SpiffWorkflow/bpmn/serializer/default/workflow.py
SpiffWorkflow/bpmn/serializer/helpers/__init__.py
SpiffWorkflow/bpmn/serializer/helpers/bpmn_converter.py
SpiffWorkflow/bpmn/serializer/helpers/dictionary.py
SpiffWorkflow/bpmn/serializer/helpers/registry.py
SpiffWorkflow/bpmn/serializer/helpers/spec.py
SpiffWorkflow/bpmn/serializer/migration/__init__.py
SpiffWorkflow/bpmn/serializer/migration/version_1_1.py
SpiffWorkflow/bpmn/serializer/migration/version_1_2.py
SpiffWorkflow/bpmn/serializer/migration/version_1_3.py
SpiffWorkflow/bpmn/serializer/migration/version_1_4.py
spiffworkflow-3.1.2.dist-info/licenses/AUTHORS
spiffworkflow-3.1.2.dist-info/licenses/COPYING
spiffworkflow-3.1.2.dist-info/METADATA
spiffworkflow-3.1.2.dist-info/WHEEL
spiffworkflow-3.1.2.dist-info/top_level.txt
spiffworkflow-3.1.2.dist-info/RECORD
