Metadata-Version: 2.4
Name: SpiffWorkflow
Version: 3.1.2
Summary: A workflow framework and BPMN/DMN Processor
Author-email: Sartography <dan@sartography.com>
License: lGPLv3
Project-URL: Homepage, https://github.com/sartography/SpiffWorkflow
Project-URL: Documentation, https://spiffworkflow.readthedocs.io
Keywords: spiff,workflow,bpmn,engine
Classifier: Development Status :: 4 - Beta
Classifier: Intended Audience :: Developers
Classifier: License :: OSI Approved :: GNU Library or Lesser General Public License (LGPL)
Classifier: Programming Language :: Python :: 3
Classifier: Topic :: Other/Nonlisted Topic
Classifier: Topic :: Software Development :: Libraries
Classifier: Topic :: Software Development :: Libraries :: Python Modules
Requires-Python: >=3.8
License-File: COPYING
License-File: AUTHORS
Requires-Dist: lxml
Provides-Extra: doc
Requires-Dist: sphinx; extra == "doc"
Requires-Dist: sphinx_rtd_theme; extra == "doc"
Provides-Extra: dev
Requires-Dist: build; extra == "dev"
Requires-Dist: coverage; extra == "dev"
Dynamic: license-file
